{
  "ME_OB_1": "ME_OB_1",
  "RI_OB_2": "RI_OB_2",
  "NCS_IB_2": "NCS_IB_2",
  "MD-W_IB_1": "MD-W_IB_1",
  "ME_IB_2": "ME_IB_2",
  "MD-N_IB_1": "MD-N_IB_1",
  "BNSF_OB_1": "BNSF_OB_1",
  "RI_IB_2": "RI_IB_2",
  "ME_IB_3": "ME_IB_3",
  "SWS_OB_1": "SWS_OB_1",
  "HC_IB_1": "HC_IB_1",
  "SWS_IB_1": "SWS_IB_1",
  "MD-W_OB_1": "MD-W_OB_1",
  "UP-NW_OB_1": "UP-NW_OB_1",
  "UP-NW_IB_2": "UP-NW_IB_2",
  "ME_IB_1": "ME_IB_1",
  "ME_OB_2": "ME_OB_2",
  "UP-N_OB_1": "UP-N_OB_1",
  "BNSF_IB_1": "BNSF_IB_1",
  "UP-NW_OB_2": "UP-NW_OB_2",
  "UP-W_IB_1": "UP-W_IB_1",
  "UP-NW_IB_1": "UP-NW_IB_1",
  "HC_OB_1": "HC_OB_1",
  "NCS_OB_1": "NCS_OB_1",
  "MD-N_OB_1": "MD-N_OB_1",
  "RI_IB_1": "RI_IB_1",
  "UP-N_IB_1": "UP-N_IB_1",
  "UP-W_OB_1": "UP-W_OB_1",
  "RI_OB_1": "RI_OB_1",
  "ME_OB_3": "ME_OB_3",
  "NCS_IB_1": "NCS_IB_1"
}